features_extraction/__init__.py
features_extraction/features_extraction.py
bacterial_image_analyzer-0.0.1.dist-info/LICENSE.txt
bacterial_image_analyzer-0.0.1.dist-info/METADATA
bacterial_image_analyzer-0.0.1.dist-info/WHEEL
bacterial_image_analyzer-0.0.1.dist-info/top_level.txt
bacterial_image_analyzer-0.0.1.dist-info/RECORD
